{
  "annotations": {
    "list": [
      {
        "builtIn": 1,
        "datasource": "-- Grafana --",
        "enable": true,
        "hide": true,
        "iconColor": "rgba(0, 211, 255, 1)",
        "name": "Annotations & Alerts",
        "type": "dashboard"
      }
    ]
  },
  "editable": true,
  "gnetId": null,
  "graphTooltip": 0,
  "id": 53,
  "iteration": 1583880838829,
  "links": [],
  "panels": [
    {
      "cacheTimeout": null,
      "colorBackground": false,
      "colorPostfix": false,
      "colorPrefix": false,
      "colorValue": true,
      "colors": [
        "#d44a3a",
        "rgba(237, 129, 40, 0.89)",
        "#299c46"
      ],
      "datasource": "SparkStreaming",
      "decimals": null,
      "format": "none",
      "gauge": {
        "maxValue": 100,
        "minValue": 0,
        "show": false,
        "thresholdLabels": false,
        "thresholdMarkers": true
      },
      "gridPos": {
        "h": 8,
        "w": 6,
        "x": 0,
        "y": 0
      },
      "id": 12,
      "interval": null,
      "links": [],
      "mappingType": 1,
      "mappingTypes": [
        {
          "name": "value to text",
          "value": 1
        },
        {
          "name": "range to text",
          "value": 2
        }
      ],
      "maxDataPoints": 100,
      "nullPointMode": "connected",
      "nullText": null,
      "options": {},
      "postfix": "",
      "postfixFontSize": "50%",
      "prefix": "",
      "prefixFontSize": "50%",
      "rangeMaps": [
        {
          "from": "null",
          "text": "N/A",
          "to": "null"
        }
      ],
      "repeat": null,
      "repeatDirection": "h",
      "sparkline": {
        "fillColor": "rgba(31, 118, 189, 0.18)",
        "full": false,
        "lineColor": "rgb(31, 120, 193)",
        "show": false,
        "ymax": null,
        "ymin": null
      },
      "tableColumn": "",
      "targets": [
        {
          "expr": "streaming_metrics{application=\"$application_ID\",executor_id=\"driver\",qty=\"applicationStatus\",type=\"streaming\"}",
          "instant": false,
          "refId": "A"
        }
      ],
      "thresholds": "1.1,2.1",
      "timeFrom": null,
      "timeShift": null,
      "title": "运行状态",
      "type": "singlestat",
      "valueFontSize": "150%",
      "valueMaps": [
        {
          "op": "=",
          "text": "停止",
          "value": "null"
        },
        {
          "op": "=",
          "text": "等待",
          "value": "0"
        },
        {
          "op": "=",
          "text": "运行",
          "value": "1"
        },
        {
          "op": "=",
          "text": "异常",
          "value": "2"
        },
        {
          "op": "=",
          "text": "停止",
          "value": "3"
        }
      ],
      "valueName": "current"
    },
    {
      "cacheTimeout": null,
      "datasource": "SparkStreaming",
      "gridPos": {
        "h": 8,
        "w": 6,
        "x": 6,
        "y": 0
      },
      "id": 14,
      "links": [],
      "options": {
        "fieldOptions": {
          "calcs": [
            "mean"
          ],
          "defaults": {
            "links": [],
            "mappings": [
              {
                "id": 0,
                "op": "=",
                "text": "0",
                "type": 1,
                "value": "null"
              }
            ],
            "max": 8,
            "min": 0,
            "nullValueMode": "connected",
            "thresholds": [
              {
                "color": "green",
                "value": null
              },
              {
                "color": "red",
                "value": 3
              }
            ],
            "title": "",
            "unit": "none"
          },
          "override": {},
          "values": false
        },
        "orientation": "horizontal",
        "showThresholdLabels": true,
        "showThresholdMarkers": true
      },
      "pluginVersion": "6.5.2",
      "targets": [
        {
          "expr": "streaming_metrics{application=\"$application_ID\",executor_id=\"driver\",qty=\"receivers\",type=\"streaming\"}",
          "refId": "A"
        }
      ],
      "timeFrom": null,
      "timeShift": null,
      "title": "消费线程数",
      "type": "gauge"
    },
    {
      "cacheTimeout": null,
      "colorBackground": false,
      "colorPrefix": false,
      "colorValue": true,
      "colors": [
        "#299c46",
        "rgba(237, 129, 40, 0.89)",
        "#d44a3a"
      ],
      "datasource": "SparkStreaming",
      "decimals": -1,
      "format": "none",
      "gauge": {
        "maxValue": 100,
        "minValue": 0,
        "show": false,
        "thresholdLabels": false,
        "thresholdMarkers": true
      },
      "gridPos": {
        "h": 8,
        "w": 6,
        "x": 12,
        "y": 0
      },
      "id": 26,
      "interval": null,
      "links": [],
      "mappingType": 1,
      "mappingTypes": [
        {
          "name": "value to text",
          "value": 1
        },
        {
          "name": "range to text",
          "value": 2
        }
      ],
      "maxDataPoints": 100,
      "nullPointMode": "connected",
      "nullText": null,
      "options": {},
      "postfix": "",
      "postfixFontSize": "50%",
      "prefix": "",
      "prefixFontSize": "50%",
      "rangeMaps": [
        {
          "from": "null",
          "text": "N/A",
          "to": "null"
        }
      ],
      "sparkline": {
        "fillColor": "rgba(31, 118, 189, 0.18)",
        "full": false,
        "lineColor": "rgb(31, 120, 193)",
        "show": false,
        "ymax": null,
        "ymin": 0
      },
      "tableColumn": "",
      "targets": [
        {
          "expr": "streaming_metrics{application=\"$application_ID\",executor_id=\"driver\",qty=\"totalCompletedBatches\",type=\"streaming\"}",
          "legendFormat": "totalCompletedBatches",
          "refId": "A"
        }
      ],
      "thresholds": "",
      "timeFrom": null,
      "timeShift": null,
      "title": "已完成批次",
      "type": "singlestat",
      "valueFontSize": "150%",
      "valueMaps": [
        {
          "op": "=",
          "text": "0",
          "value": "null"
        }
      ],
      "valueName": "avg"
    },
    {
      "cacheTimeout": null,
      "colorBackground": false,
      "colorValue": false,
      "colors": [
        "#299c46",
        "rgba(237, 129, 40, 0.89)",
        "#d44a3a"
      ],
      "datasource": "SparkStreaming",
      "format": "none",
      "gauge": {
        "maxValue": 100,
        "minValue": 0,
        "show": false,
        "thresholdLabels": false,
        "thresholdMarkers": true
      },
      "gridPos": {
        "h": 8,
        "w": 6,
        "x": 18,
        "y": 0
      },
      "id": 24,
      "interval": null,
      "links": [],
      "mappingType": 1,
      "mappingTypes": [
        {
          "name": "value to text",
          "value": 1
        },
        {
          "name": "range to text",
          "value": 2
        }
      ],
      "maxDataPoints": 100,
      "nullPointMode": "connected",
      "nullText": null,
      "options": {},
      "pluginVersion": "6.5.2",
      "postfix": "",
      "postfixFontSize": "50%",
      "prefix": "",
      "prefixFontSize": "50%",
      "rangeMaps": [
        {
          "from": "null",
          "text": "N/A",
          "to": "null"
        }
      ],
      "sparkline": {
        "fillColor": "rgba(31, 118, 189, 0.18)",
        "full": false,
        "lineColor": "#3274D9",
        "show": true,
        "ymax": null,
        "ymin": 0
      },
      "tableColumn": "",
      "targets": [
        {
          "expr": "streaming_metrics{application=\"$application_ID\",executor_id=\"driver\",qty=\"totalProcessedRecords\",type=\"streaming\"}",
          "legendFormat": "totalProcessedRecords",
          "refId": "A"
        }
      ],
      "thresholds": "",
      "timeFrom": null,
      "timeShift": null,
      "title": "已处理记录数",
      "type": "singlestat",
      "valueFontSize": "150%",
      "valueMaps": [
        {
          "op": "=",
          "text": "0",
          "value": "null"
        }
      ],
      "valueName": "current"
    },
    {
      "aliasColors": {},
      "bars": false,
      "dashLength": 10,
      "dashes": false,
      "datasource": "SparkStreaming",
      "description": "",
      "fill": 1,
      "fillGradient": 0,
      "gridPos": {
        "h": 8,
        "w": 12,
        "x": 0,
        "y": 8
      },
      "hiddenSeries": false,
      "id": 30,
      "interval": "",
      "legend": {
        "alignAsTable": false,
        "avg": false,
        "current": true,
        "max": false,
        "min": false,
        "rightSide": false,
        "show": true,
        "total": false,
        "values": true
      },
      "lines": true,
      "linewidth": 1,
      "nullPointMode": "null",
      "options": {
        "dataLinks": []
      },
      "percentage": false,
      "pointradius": 2,
      "points": true,
      "renderer": "flot",
      "seriesOverrides": [],
      "spaceLength": 10,
      "stack": false,
      "steppedLine": false,
      "targets": [
        {
          "expr": "streaming_metrics{application=\"$application_ID\",executor_id=\"driver\",qty=\"lastCompletedBatch_processRate\",type=\"streaming\"}",
          "legendFormat": "程序处理速率 条/秒",
          "refId": "A"
        },
        {
          "expr": "(rate(streaming_metrics{application=\"$application_ID\",executor_id=\"driver\",qty=\"totalReceivedRecords\",type=\"streaming\"}[5m]))",
          "instant": false,
          "legendFormat": "接收速率 条/秒",
          "refId": "B"
        },
        {
          "expr": "(increase(streaming_metrics{application=\"$application_ID\",executor_id=\"driver\",qty=\"totalProcessedRecords\",type=\"streaming\"}[5m])) / (5 * 60.0)",
          "legendFormat": "消费速率 条/秒",
          "refId": "C"
        }
      ],
      "thresholds": [],
      "timeFrom": null,
      "timeRegions": [],
      "timeShift": null,
      "title": "记录处理速率概览",
      "tooltip": {
        "shared": true,
        "sort": 0,
        "value_type": "individual"
      },
      "transparent": true,
      "type": "graph",
      "xaxis": {
        "buckets": null,
        "mode": "time",
        "name": null,
        "show": true,
        "values": []
      },
      "yaxes": [
        {
          "format": "short",
          "label": "",
          "logBase": 1,
          "max": null,
          "min": null,
          "show": true
        },
        {
          "format": "short",
          "label": null,
          "logBase": 1,
          "max": null,
          "min": null,
          "show": true
        }
      ],
      "yaxis": {
        "align": false,
        "alignLevel": null
      }
    },
    {
      "aliasColors": {},
      "bars": false,
      "dashLength": 10,
      "dashes": false,
      "datasource": "SparkStreaming",
      "fill": 1,
      "fillGradient": 0,
      "gridPos": {
        "h": 6,
        "w": 24,
        "x": 0,
        "y": 16
      },
      "hiddenSeries": false,
      "id": 28,
      "legend": {
        "alignAsTable": true,
        "avg": true,
        "current": true,
        "max": true,
        "min": true,
        "rightSide": true,
        "show": true,
        "total": false,
        "values": true
      },
      "lines": true,
      "linewidth": 1,
      "maxPerRow": 2,
      "nullPointMode": "null as zero",
      "options": {
        "dataLinks": []
      },
      "percentage": false,
      "pointradius": 1,
      "points": true,
      "renderer": "flot",
      "repeat": "application_ID",
      "repeatDirection": "h",
      "scopedVars": {
        "application_ID": {
          "selected": true,
          "text": "local-1583669715397",
          "value": "local-1583669715397"
        }
      },
      "seriesOverrides": [],
      "spaceLength": 10,
      "stack": false,
      "steppedLine": false,
      "targets": [
        {
          "expr": "streaming_metrics{application=\"$application_ID\",executor_id=\"driver\",qty=\"lastCompletedBatch_totalDelay\",type=\"streaming\"}",
          "legendFormat": "总耗时",
          "refId": "A"
        },
        {
          "expr": "streaming_metrics{application=\"$application_ID\",executor_id=\"driver\",qty=\"lastCompletedBatch_processingDelay\",type=\"streaming\"}",
          "legendFormat": "运行耗时",
          "refId": "B"
        },
        {
          "expr": "streaming_metrics{application=\"$application_ID\",executor_id=\"driver\",qty=\"lastCompletedBatch_schedulingDelay\",type=\"streaming\"}",
          "legendFormat": "调度耗时",
          "refId": "C"
        }
      ],
      "thresholds": [],
      "timeFrom": null,
      "timeRegions": [],
      "timeShift": null,
      "title": "单批次耗时：ms",
      "tooltip": {
        "shared": true,
        "sort": 0,
        "value_type": "individual"
      },
      "transparent": true,
      "type": "graph",
      "xaxis": {
        "buckets": null,
        "mode": "time",
        "name": null,
        "show": true,
        "values": []
      },
      "yaxes": [
        {
          "format": "short",
          "label": "ms",
          "logBase": 1,
          "max": null,
          "min": null,
          "show": true
        },
        {
          "format": "short",
          "label": null,
          "logBase": 1,
          "max": null,
          "min": null,
          "show": true
        }
      ],
      "yaxis": {
        "align": false,
        "alignLevel": null
      }
    },
    {
      "aliasColors": {},
      "bars": false,
      "dashLength": 10,
      "dashes": false,
      "datasource": "SparkStreaming",
      "fill": 1,
      "fillGradient": 0,
      "gridPos": {
        "h": 8,
        "w": 12,
        "x": 0,
        "y": 22
      },
      "hiddenSeries": false,
      "id": 20,
      "legend": {
        "avg": false,
        "current": false,
        "max": false,
        "min": false,
        "show": true,
        "total": false,
        "values": false
      },
      "lines": true,
      "linewidth": 1,
      "nullPointMode": "null",
      "options": {
        "dataLinks": []
      },
      "percentage": false,
      "pointradius": 2,
      "points": false,
      "renderer": "flot",
      "seriesOverrides": [],
      "spaceLength": 10,
      "stack": false,
      "steppedLine": false,
      "targets": [
        {
          "expr": "(increase(streaming_metrics{application=\"$application_ID\",executor_id=\"driver\",qty=\"totalCompletedBatches\",type=\"streaming\"}[1m])) / 60",
          "instant": false,
          "legendFormat": "处理速率 批/秒",
          "refId": "A"
        }
      ],
      "thresholds": [
        {
          "colorMode": "critical",
          "fill": true,
          "line": true,
          "op": "lt",
          "value": 1,
          "yaxis": "left"
        }
      ],
      "timeFrom": null,
      "timeRegions": [],
      "timeShift": null,
      "title": "批次处理速率 / 分",
      "tooltip": {
        "shared": true,
        "sort": 0,
        "value_type": "individual"
      },
      "type": "graph",
      "xaxis": {
        "buckets": null,
        "mode": "time",
        "name": null,
        "show": true,
        "values": []
      },
      "yaxes": [
        {
          "format": "short",
          "label": null,
          "logBase": 1,
          "max": null,
          "min": null,
          "show": true
        },
        {
          "format": "short",
          "label": null,
          "logBase": 1,
          "max": null,
          "min": null,
          "show": true
        }
      ],
      "yaxis": {
        "align": false,
        "alignLevel": null
      }
    },
    {
      "aliasColors": {},
      "bars": false,
      "dashLength": 10,
      "dashes": false,
      "datasource": "SparkStreaming",
      "fill": 1,
      "fillGradient": 0,
      "gridPos": {
        "h": 8,
        "w": 12,
        "x": 12,
        "y": 22
      },
      "hiddenSeries": false,
      "id": 22,
      "legend": {
        "avg": false,
        "current": true,
        "max": false,
        "min": false,
        "show": true,
        "total": false,
        "values": true
      },
      "lines": true,
      "linewidth": 1,
      "nullPointMode": "null",
      "options": {
        "dataLinks": []
      },
      "percentage": false,
      "pointradius": 2,
      "points": true,
      "renderer": "flot",
      "seriesOverrides": [],
      "spaceLength": 10,
      "stack": false,
      "steppedLine": false,
      "targets": [
        {
          "expr": "streaming_metrics{application=\"$application_ID\",executor_id=\"driver\",qty=\"lastReceivedBatch_records\",type=\"streaming\"}",
          "format": "time_series",
          "instant": false,
          "interval": "",
          "intervalFactor": 1,
          "legendFormat": "最近接收批次记录数",
          "refId": "A"
        },
        {
          "expr": "streaming_metrics{application=\"$application_ID\",executor_id=\"driver\",qty=\"lastCompletedBatch_records\",type=\"streaming\"}",
          "legendFormat": "最近完成批次记录数",
          "refId": "B"
        }
      ],
      "thresholds": [],
      "timeFrom": null,
      "timeRegions": [],
      "timeShift": null,
      "title": "单批次记录数量",
      "tooltip": {
        "shared": true,
        "sort": 0,
        "value_type": "individual"
      },
      "type": "graph",
      "xaxis": {
        "buckets": null,
        "mode": "time",
        "name": null,
        "show": true,
        "values": []
      },
      "yaxes": [
        {
          "format": "short",
          "label": null,
          "logBase": 1,
          "max": null,
          "min": "0",
          "show": true
        },
        {
          "format": "short",
          "label": null,
          "logBase": 1,
          "max": null,
          "min": null,
          "show": true
        }
      ],
      "yaxis": {
        "align": false,
        "alignLevel": null
      }
    },
    {
      "aliasColors": {},
      "bars": false,
      "dashLength": 10,
      "dashes": false,
      "datasource": "SparkStreaming",
      "decimals": null,
      "fill": 1,
      "fillGradient": 0,
      "gridPos": {
        "h": 8,
        "w": 12,
        "x": 0,
        "y": 30
      },
      "hiddenSeries": false,
      "id": 18,
      "legend": {
        "avg": false,
        "current": true,
        "hideZero": false,
        "max": false,
        "min": false,
        "show": true,
        "total": false,
        "values": true
      },
      "lines": true,
      "linewidth": 1,
      "nullPointMode": "null as zero",
      "options": {
        "dataLinks": []
      },
      "percentage": false,
      "pointradius": 2,
      "points": false,
      "renderer": "flot",
      "seriesOverrides": [],
      "spaceLength": 10,
      "stack": false,
      "steppedLine": false,
      "targets": [
        {
          "expr": "streaming_metrics{application=\"$application_ID\",executor_id=\"driver\",qty=\"totalReceivedRecords\",type=\"streaming\"}",
          "legendFormat": "接收记录合计",
          "refId": "A"
        },
        {
          "expr": "streaming_metrics{application=\"$application_ID\",executor_id=\"driver\",qty=\"totalProcessedRecords\",type=\"streaming\"}",
          "legendFormat": "处理记录合计",
          "refId": "B"
        }
      ],
      "thresholds": [],
      "timeFrom": null,
      "timeRegions": [],
      "timeShift": null,
      "title": "记录数量汇总",
      "tooltip": {
        "shared": true,
        "sort": 0,
        "value_type": "individual"
      },
      "type": "graph",
      "xaxis": {
        "buckets": null,
        "mode": "time",
        "name": null,
        "show": true,
        "values": []
      },
      "yaxes": [
        {
          "format": "short",
          "label": null,
          "logBase": 1,
          "max": null,
          "min": "0",
          "show": true
        },
        {
          "format": "short",
          "label": null,
          "logBase": 1,
          "max": null,
          "min": null,
          "show": true
        }
      ],
      "yaxis": {
        "align": false,
        "alignLevel": null
      }
    },
    {
      "aliasColors": {},
      "bars": false,
      "dashLength": 10,
      "dashes": false,
      "datasource": "SparkStreaming",
      "fill": 1,
      "fillGradient": 0,
      "gridPos": {
        "h": 8,
        "w": 12,
        "x": 12,
        "y": 30
      },
      "hiddenSeries": false,
      "id": 16,
      "legend": {
        "avg": false,
        "current": true,
        "max": false,
        "min": false,
        "show": true,
        "total": false,
        "values": true
      },
      "lines": true,
      "linewidth": 1,
      "nullPointMode": "null as zero",
      "options": {
        "dataLinks": []
      },
      "percentage": false,
      "pointradius": 2,
      "points": true,
      "renderer": "flot",
      "seriesOverrides": [],
      "spaceLength": 10,
      "stack": false,
      "steppedLine": false,
      "targets": [
        {
          "expr": "streaming_metrics{application=\"$application_ID\",executor_id=\"driver\",qty=\"waitingBatches\",type=\"streaming\"}",
          "hide": false,
          "legendFormat": "等待批次合计",
          "refId": "A"
        },
        {
          "expr": "streaming_metrics{application=\"$application_ID\",executor_id=\"driver\",qty=\"unprocessedBatches\",type=\"streaming\"}",
          "legendFormat": "未处理批次合计",
          "refId": "B"
        },
        {
          "expr": "streaming_metrics{application=\"$application_ID\",executor_id=\"driver\",qty=\"runningBatches\",type=\"streaming\"}",
          "legendFormat": "运行批次合计",
          "refId": "C"
        }
      ],
      "thresholds": [
        {
          "colorMode": "critical",
          "fill": true,
          "line": true,
          "op": "gt",
          "value": 10,
          "yaxis": "left"
        }
      ],
      "timeFrom": null,
      "timeRegions": [],
      "timeShift": null,
      "title": "批次数量汇总",
      "tooltip": {
        "shared": true,
        "sort": 0,
        "value_type": "individual"
      },
      "type": "graph",
      "xaxis": {
        "buckets": null,
        "mode": "time",
        "name": null,
        "show": true,
        "values": []
      },
      "yaxes": [
        {
          "format": "short",
          "label": "",
          "logBase": 1,
          "max": null,
          "min": null,
          "show": true
        },
        {
          "format": "short",
          "label": null,
          "logBase": 1,
          "max": null,
          "min": null,
          "show": true
        }
      ],
      "yaxis": {
        "align": false,
        "alignLevel": null
      }
    },
    {
      "aliasColors": {},
      "bars": false,
      "dashLength": 10,
      "dashes": false,
      "datasource": "SparkStreaming",
      "editable": true,
      "error": false,
      "fill": 1,
      "fillGradient": 0,
      "grid": {},
      "gridPos": {
        "h": 7,
        "w": 24,
        "x": 0,
        "y": 38
      },
      "hiddenSeries": false,
      "id": 10,
      "legend": {
        "avg": false,
        "current": false,
        "max": false,
        "min": false,
        "show": true,
        "total": false,
        "values": false
      },
      "lines": true,
      "linewidth": 2,
      "links": [],
      "nullPointMode": "connected",
      "options": {
        "dataLinks": []
      },
      "percentage": false,
      "pointradius": 5,
      "points": false,
      "renderer": "flot",
      "seriesOverrides": [
        {
          "alias": "completeTasks",
          "yaxis": 2
        }
      ],
      "spaceLength": 10,
      "stack": false,
      "steppedLine": false,
      "targets": [
        {
          "expr": "sum(executor_tasks{application=\"$application_ID\", qty!~\"maxPool_size\"}) by (qty)",
          "intervalFactor": 2,
          "legendFormat": "{{qty}}",
          "refId": "B",
          "step": 2,
          "target": ""
        }
      ],
      "thresholds": [],
      "timeFrom": null,
      "timeRegions": [],
      "timeShift": null,
      "title": "任务数",
      "tooltip": {
        "shared": true,
        "sort": 0,
        "value_type": "cumulative"
      },
      "type": "graph",
      "xaxis": {
        "buckets": null,
        "mode": "time",
        "name": null,
        "show": true,
        "values": []
      },
      "yaxes": [
        {
          "format": "short",
          "logBase": 1,
          "max": null,
          "min": null,
          "show": true
        },
        {
          "format": "short",
          "logBase": 1,
          "max": null,
          "min": null,
          "show": true
        }
      ],
      "yaxis": {
        "align": false,
        "alignLevel": null
      }
    },
    {
      "aliasColors": {},
      "bars": false,
      "dashLength": 10,
      "dashes": false,
      "datasource": "SparkStreaming",
      "editable": true,
      "error": false,
      "fill": 0,
      "fillGradient": 0,
      "grid": {},
      "gridPos": {
        "h": 7,
        "w": 12,
        "x": 0,
        "y": 45
      },
      "hiddenSeries": false,
      "id": 4,
      "legend": {
        "avg": false,
        "current": false,
        "max": false,
        "min": false,
        "show": true,
        "total": false,
        "values": false
      },
      "lines": true,
      "linewidth": 2,
      "links": [],
      "nullPointMode": "connected",
      "options": {
        "dataLinks": []
      },
      "percentage": false,
      "pointradius": 5,
      "points": false,
      "renderer": "flot",
      "seriesOverrides": [],
      "spaceLength": 10,
      "stack": false,
      "steppedLine": false,
      "targets": [
        {
          "expr": "jvm_memory_usage{mem_type=\"heap\", qty=\"usage\", application=\"$application_ID\", executor_id=\"driver\"}",
          "intervalFactor": 2,
          "legendFormat": "{{executor_id}}",
          "metric": "jvm_memory_usage",
          "refId": "A",
          "step": 2,
          "target": ""
        }
      ],
      "thresholds": [],
      "timeFrom": null,
      "timeRegions": [],
      "timeShift": null,
      "title": "Driver Heap Usage",
      "tooltip": {
        "shared": true,
        "sort": 0,
        "value_type": "cumulative"
      },
      "type": "graph",
      "xaxis": {
        "buckets": null,
        "mode": "time",
        "name": null,
        "show": true,
        "values": []
      },
      "yaxes": [
        {
          "format": "short",
          "logBase": 1,
          "max": null,
          "min": 0,
          "show": true
        },
        {
          "format": "short",
          "logBase": 1,
          "max": null,
          "min": null,
          "show": true
        }
      ],
      "yaxis": {
        "align": false,
        "alignLevel": null
      }
    },
    {
      "aliasColors": {},
      "bars": false,
      "dashLength": 10,
      "dashes": false,
      "datasource": "SparkStreaming",
      "editable": true,
      "error": false,
      "fill": 1,
      "fillGradient": 0,
      "grid": {},
      "gridPos": {
        "h": 7,
        "w": 12,
        "x": 12,
        "y": 45
      },
      "hiddenSeries": false,
      "id": 5,
      "legend": {
        "avg": false,
        "current": false,
        "max": false,
        "min": false,
        "show": true,
        "total": false,
        "values": false
      },
      "lines": true,
      "linewidth": 2,
      "links": [],
      "nullPointMode": "connected",
      "options": {
        "dataLinks": []
      },
      "percentage": false,
      "pointradius": 5,
      "points": false,
      "renderer": "flot",
      "seriesOverrides": [],
      "spaceLength": 10,
      "stack": false,
      "steppedLine": false,
      "targets": [
        {
          "expr": "jvm_memory_pools{executor_id=\"driver\", application=\"$application_ID\",qty=\"used\"}",
          "intervalFactor": 2,
          "legendFormat": "{{mem_type}}",
          "metric": "jvm_memory_pools",
          "refId": "A",
          "step": 2,
          "target": ""
        }
      ],
      "thresholds": [],
      "timeFrom": null,
      "timeRegions": [],
      "timeShift": null,
      "title": "Driver JVM Memory Pools",
      "tooltip": {
        "shared": true,
        "sort": 0,
        "value_type": "cumulative"
      },
      "type": "graph",
      "xaxis": {
        "buckets": null,
        "mode": "time",
        "name": null,
        "show": true,
        "values": []
      },
      "yaxes": [
        {
          "format": "short",
          "logBase": 1,
          "max": null,
          "min": null,
          "show": true
        },
        {
          "format": "short",
          "logBase": 1,
          "max": null,
          "min": null,
          "show": true
        }
      ],
      "yaxis": {
        "align": false,
        "alignLevel": null
      }
    },
    {
      "aliasColors": {},
      "bars": false,
      "dashLength": 10,
      "dashes": false,
      "datasource": "SparkStreaming",
      "editable": true,
      "error": false,
      "fill": 0,
      "fillGradient": 0,
      "grid": {},
      "gridPos": {
        "h": 7,
        "w": 8,
        "x": 0,
        "y": 52
      },
      "hiddenSeries": false,
      "id": 6,
      "legend": {
        "avg": false,
        "current": false,
        "max": false,
        "min": false,
        "show": false,
        "total": false,
        "values": false
      },
      "lines": true,
      "linewidth": 2,
      "links": [],
      "nullPointMode": "connected",
      "options": {
        "dataLinks": []
      },
      "percentage": false,
      "pointradius": 5,
      "points": false,
      "renderer": "flot",
      "seriesOverrides": [],
      "spaceLength": 10,
      "stack": false,
      "steppedLine": false,
      "targets": [
        {
          "expr": "jvm_memory_usage{mem_type=\"heap\", qty=\"usage\", application=\"$application_ID\", executor_id!~\"driver\"} ",
          "intervalFactor": 2,
          "legendFormat": "{{executor_id}}",
          "metric": "jvm_memory_usage",
          "refId": "A",
          "step": 2,
          "target": ""
        }
      ],
      "thresholds": [],
      "timeFrom": null,
      "timeRegions": [],
      "timeShift": null,
      "title": "Executor Heap Usage",
      "tooltip": {
        "shared": true,
        "sort": 0,
        "value_type": "cumulative"
      },
      "type": "graph",
      "xaxis": {
        "buckets": null,
        "mode": "time",
        "name": null,
        "show": true,
        "values": []
      },
      "yaxes": [
        {
          "format": "short",
          "logBase": 1,
          "max": null,
          "min": null,
          "show": true
        },
        {
          "format": "short",
          "logBase": 1,
          "max": null,
          "min": null,
          "show": true
        }
      ],
      "yaxis": {
        "align": false,
        "alignLevel": null
      }
    },
    {
      "aliasColors": {},
      "bars": false,
      "dashLength": 10,
      "dashes": false,
      "datasource": "SparkStreaming",
      "editable": true,
      "error": false,
      "fill": 0,
      "fillGradient": 0,
      "grid": {},
      "gridPos": {
        "h": 7,
        "w": 8,
        "x": 8,
        "y": 52
      },
      "hiddenSeries": false,
      "id": 7,
      "legend": {
        "avg": false,
        "current": false,
        "max": false,
        "min": false,
        "show": false,
        "total": false,
        "values": false
      },
      "lines": true,
      "linewidth": 2,
      "links": [],
      "nullPointMode": "connected",
      "options": {
        "dataLinks": []
      },
      "percentage": false,
      "pointradius": 5,
      "points": false,
      "renderer": "flot",
      "seriesOverrides": [],
      "spaceLength": 10,
      "stack": false,
      "steppedLine": false,
      "targets": [
        {
          "expr": "jvm_memory_pools{executor_id!~\"driver\", application=\"$application_ID\",qty=\"usage\", mem_type=\"PS-Eden-Space\"}",
          "intervalFactor": 2,
          "legendFormat": "{{executor_id}}",
          "metric": "jvm_memory_pools",
          "refId": "A",
          "step": 2,
          "target": ""
        }
      ],
      "thresholds": [],
      "timeFrom": null,
      "timeRegions": [],
      "timeShift": null,
      "title": "Executor Eden-Space",
      "tooltip": {
        "shared": true,
        "sort": 0,
        "value_type": "cumulative"
      },
      "type": "graph",
      "xaxis": {
        "buckets": null,
        "mode": "time",
        "name": null,
        "show": true,
        "values": []
      },
      "yaxes": [
        {
          "format": "short",
          "logBase": 1,
          "max": null,
          "min": null,
          "show": true
        },
        {
          "format": "short",
          "logBase": 1,
          "max": null,
          "min": null,
          "show": true
        }
      ],
      "yaxis": {
        "align": false,
        "alignLevel": null
      }
    },
    {
      "aliasColors": {},
      "bars": false,
      "dashLength": 10,
      "dashes": false,
      "datasource": "SparkStreaming",
      "editable": true,
      "error": false,
      "fill": 0,
      "fillGradient": 0,
      "grid": {},
      "gridPos": {
        "h": 7,
        "w": 8,
        "x": 16,
        "y": 52
      },
      "hiddenSeries": false,
      "id": 9,
      "legend": {
        "avg": false,
        "current": false,
        "max": false,
        "min": false,
        "show": true,
        "total": false,
        "values": false
      },
      "lines": true,
      "linewidth": 2,
      "links": [],
      "nullPointMode": "connected",
      "options": {
        "dataLinks": []
      },
      "percentage": false,
      "pointradius": 5,
      "points": false,
      "renderer": "flot",
      "seriesOverrides": [],
      "spaceLength": 10,
      "stack": false,
      "steppedLine": false,
      "targets": [
        {
          "expr": "jvm_memory_pools{executor_id!~\"driver\", application=\"$application_ID\",qty=\"usage\", mem_type=\"PS-Old-Gen\"}",
          "intervalFactor": 2,
          "legendFormat": "{{executor_id}}",
          "metric": "jvm_memory_pools",
          "refId": "A",
          "step": 2,
          "target": ""
        }
      ],
      "thresholds": [],
      "timeFrom": null,
      "timeRegions": [],
      "timeShift": null,
      "title": "Executor Old-Gen",
      "tooltip": {
        "shared": true,
        "sort": 0,
        "value_type": "cumulative"
      },
      "type": "graph",
      "xaxis": {
        "buckets": null,
        "mode": "time",
        "name": null,
        "show": true,
        "values": []
      },
      "yaxes": [
        {
          "format": "short",
          "logBase": 1,
          "max": null,
          "min": null,
          "show": true
        },
        {
          "format": "short",
          "logBase": 1,
          "max": null,
          "min": null,
          "show": true
        }
      ],
      "yaxis": {
        "align": false,
        "alignLevel": null
      }
    },
    {
      "aliasColors": {},
      "bars": false,
      "dashLength": 10,
      "dashes": false,
      "datasource": "SparkStreaming",
      "editable": true,
      "error": false,
      "fill": 0,
      "fillGradient": 0,
      "grid": {},
      "gridPos": {
        "h": 7,
        "w": 8,
        "x": 0,
        "y": 59
      },
      "hiddenSeries": false,
      "id": 1,
      "legend": {
        "avg": false,
        "current": false,
        "max": false,
        "min": false,
        "show": true,
        "total": false,
        "values": false
      },
      "lines": true,
      "linewidth": 2,
      "links": [],
      "nullPointMode": "connected",
      "options": {
        "dataLinks": []
      },
      "percentage": false,
      "pointradius": 5,
      "points": false,
      "renderer": "flot",
      "seriesOverrides": [
        {
          "alias": "total",
          "color": "#F2C96D",
          "linewidth": 7,
          "yaxis": 2,
          "zindex": 3
        }
      ],
      "spaceLength": 10,
      "stack": false,
      "steppedLine": false,
      "targets": [
        {
          "expr": "filesystem_usage{qty=\"read_bytes\", fs_type=\"hdfs\", application=\"$application_ID\"}",
          "intervalFactor": 2,
          "legendFormat": "{{executor_id}}",
          "metric": "filesystem_usage",
          "refId": "A",
          "step": 2,
          "target": ""
        },
        {
          "expr": "sum(filesystem_usage{qty=\"read_bytes\", fs_type=\"hdfs\", application=\"$application_ID\"})",
          "intervalFactor": 2,
          "legendFormat": "total",
          "metric": "filesystem_usage",
          "refId": "B",
          "step": 2,
          "target": ""
        }
      ],
      "thresholds": [],
      "timeFrom": null,
      "timeRegions": [],
      "timeShift": null,
      "title": "Executor HDFS reads",
      "tooltip": {
        "shared": true,
        "sort": 0,
        "value_type": "cumulative"
      },
      "type": "graph",
      "xaxis": {
        "buckets": null,
        "mode": "time",
        "name": null,
        "show": true,
        "values": []
      },
      "yaxes": [
        {
          "format": "short",
          "logBase": 1,
          "max": null,
          "min": 0,
          "show": true
        },
        {
          "format": "short",
          "logBase": 1,
          "max": null,
          "min": null,
          "show": true
        }
      ],
      "yaxis": {
        "align": false,
        "alignLevel": null
      }
    },
    {
      "aliasColors": {},
      "bars": false,
      "dashLength": 10,
      "dashes": false,
      "datasource": "SparkStreaming",
      "editable": true,
      "error": false,
      "fill": 1,
      "fillGradient": 0,
      "grid": {},
      "gridPos": {
        "h": 7,
        "w": 8,
        "x": 8,
        "y": 59
      },
      "hiddenSeries": false,
      "id": 2,
      "legend": {
        "avg": false,
        "current": false,
        "max": false,
        "min": false,
        "show": false,
        "total": false,
        "values": false
      },
      "lines": true,
      "linewidth": 2,
      "links": [],
      "nullPointMode": "connected",
      "options": {
        "dataLinks": []
      },
      "percentage": false,
      "pointradius": 5,
      "points": false,
      "renderer": "flot",
      "seriesOverrides": [],
      "spaceLength": 10,
      "stack": true,
      "steppedLine": false,
      "targets": [
        {
          "expr": "filesystem_usage{qty=\"write_bytes\", fs_type=\"hdfs\", application=\"$application_ID\"}",
          "intervalFactor": 2,
          "legendFormat": "{{executor_id}}",
          "metric": "filesystem_usage",
          "refId": "A",
          "step": 2,
          "target": ""
        }
      ],
      "thresholds": [],
      "timeFrom": null,
      "timeRegions": [],
      "timeShift": null,
      "title": "Executor HDFS writes",
      "tooltip": {
        "shared": true,
        "sort": 0,
        "value_type": "cumulative"
      },
      "type": "graph",
      "xaxis": {
        "buckets": null,
        "mode": "time",
        "name": null,
        "show": true,
        "values": []
      },
      "yaxes": [
        {
          "format": "short",
          "logBase": 1,
          "max": null,
          "min": null,
          "show": true
        },
        {
          "format": "short",
          "logBase": 1,
          "max": null,
          "min": null,
          "show": true
        }
      ],
      "yaxis": {
        "align": false,
        "alignLevel": null
      }
    },
    {
      "aliasColors": {},
      "bars": false,
      "dashLength": 10,
      "dashes": false,
      "datasource": "SparkStreaming",
      "editable": true,
      "error": false,
      "fill": 1,
      "fillGradient": 0,
      "grid": {},
      "gridPos": {
        "h": 7,
        "w": 8,
        "x": 16,
        "y": 59
      },
      "hiddenSeries": false,
      "id": 3,
      "legend": {
        "avg": false,
        "current": false,
        "max": false,
        "min": false,
        "show": true,
        "total": false,
        "values": false
      },
      "lines": true,
      "linewidth": 2,
      "links": [],
      "nullPointMode": "connected",
      "options": {
        "dataLinks": []
      },
      "percentage": false,
      "pointradius": 5,
      "points": false,
      "renderer": "flot",
      "seriesOverrides": [
        {
          "alias": "total",
          "yaxis": 2
        }
      ],
      "spaceLength": 10,
      "stack": true,
      "steppedLine": false,
      "targets": [
        {
          "expr": "avg(rate(filesystem_usage{qty=\"read_bytes\", fs_type=\"hdfs\", application=\"$application_ID\"}[1m]))",
          "intervalFactor": 1,
          "legendFormat": "average",
          "metric": "filesystem_usage",
          "refId": "A",
          "step": 1,
          "target": ""
        },
        {
          "expr": "sum(rate(filesystem_usage{qty=\"read_bytes\", fs_type=\"hdfs\", application=\"$application_ID\"}[1m]))",
          "intervalFactor": 1,
          "legendFormat": "total",
          "metric": "filesystem_usage",
          "refId": "B",
          "step": 1,
          "target": ""
        }
      ],
      "thresholds": [],
      "timeFrom": null,
      "timeRegions": [],
      "timeShift": null,
      "title": "HDFS Read Rate / s",
      "tooltip": {
        "shared": true,
        "sort": 0,
        "value_type": "cumulative"
      },
      "type": "graph",
      "xaxis": {
        "buckets": null,
        "mode": "time",
        "name": null,
        "show": true,
        "values": []
      },
      "yaxes": [
        {
          "format": "short",
          "logBase": 1,
          "max": null,
          "min": null,
          "show": true
        },
        {
          "format": "short",
          "logBase": 1,
          "max": null,
          "min": null,
          "show": true
        }
      ],
      "yaxis": {
        "align": false,
        "alignLevel": null
      }
    }
  ],
  "refresh": "5s",
  "schemaVersion": 21,
  "style": "dark",
  "tags": [],
  "templating": {
    "list": [
      {
        "allFormat": "glob",
        "allValue": null,
        "current": {
          "text": "local-1583669715397",
          "value": "local-1583669715397"
        },
        "datasource": "SparkStreaming",
        "definition": "label_values(application)",
        "hide": 0,
        "includeAll": false,
        "label": null,
        "multi": false,
        "multiFormat": "glob",
        "name": "application_ID",
        "options": [],
        "query": "label_values(application)",
        "refresh": 2,
        "refresh_on_load": false,
        "regex": "",
        "skipUrlSync": false,
        "sort": 2,
        "tagValuesQuery": "",
        "tags": [],
        "tagsQuery": "",
        "type": "query",
        "useTags": false
      }
    ]
  },
  "time": {
    "from": "now-5m",
    "to": "now"
  },
  "timepicker": {
    "now": true,
    "refresh_intervals": [
      "5s",
      "10s",
      "30s",
      "1m",
      "5m",
      "15m",
      "30m",
      "1h",
      "2h",
      "1d"
    ],
    "time_options": [
      "5m",
      "15m",
      "1h",
      "6h",
      "12h",
      "24h",
      "2d",
      "7d",
      "30d"
    ]
  },
  "timezone": "browser",
  "title": "流处理任务详情",
  "uid": "v4eIWwlZk",
  "version": 16
}